CHANGELOG.txt
LICENSE.txt
MANIFEST.in
README.txt
setup.py
Lance/__init__.py
chrisel.egg-info/PKG-INFO
chrisel.egg-info/SOURCES.txt
chrisel.egg-info/dependency_links.txt
chrisel.egg-info/top_level.txt