Metadata-Version: 2.1
Name: chrisel
Version: 0.0.1
Summary: A very basic calci
Home-page: UNKNOWN
Author: Lance Cerejo
Author-email: shauncchaudhary@gmail.com
License: MIT
Keywords: calci
Platform: UNKNOWN
Classifier: Development Status :: 5 - Production/Stable
Classifier: Intended Audience :: Education
Classifier: Operating System :: Microsoft :: Windows :: Windows 10
Classifier: License :: OSI Approved :: MIT License
Classifier: Programming Language :: Python :: 3
License-File: LICENSE.txt
